xpublish_wms/__init__.py
xpublish_wms/_version.py
xpublish_wms/logger.py
xpublish_wms/plugin.py
xpublish_wms/query.py
xpublish_wms/utils.py
xpublish_wms/grids/__init__.py
xpublish_wms/grids/fvcom.py
xpublish_wms/grids/grid.py
xpublish_wms/grids/hycom.py
xpublish_wms/grids/irregular.py
xpublish_wms/grids/regular.py
xpublish_wms/grids/roms.py
xpublish_wms/grids/selfe.py
xpublish_wms/grids/triangular.py
xpublish_wms/wms/__init__.py
xpublish_wms/wms/get_capabilities.py
xpublish_wms/wms/get_feature_info.py
xpublish_wms/wms/get_legend_info.py
xpublish_wms/wms/get_map.py
xpublish_wms/wms/get_metadata.py
xpublish_wms-0.13.3.dist-info/licenses/LICENSE.txt
xpublish_wms-0.13.3.dist-info/METADATA
xpublish_wms-0.13.3.dist-info/WHEEL
xpublish_wms-0.13.3.dist-info/entry_points.txt
xpublish_wms-0.13.3.dist-info/top_level.txt
xpublish_wms-0.13.3.dist-info/RECORD
