Metadata-Version: 2.4
Name: xpublish_wms
Version: 0.13.3
Summary: WMS plugin for xpublish
Author-email: Matthew Iannucci <matt@earthmover.io>
License: Copyright 2017 AUTHOR NAME
Project-URL: Homepage, https://github.com/xpublish-community/xpublish-wms
Keywords: xarray,xpublish,wms
Classifier: Development Status :: 5 - Production/Stable
Classifier: Intended Audience :: Science/Research
Classifier: Operating System :: OS Independent
Classifier: License :: OSI Approved :: BSD License
Classifier: Programming Language :: Python
Classifier: Programming Language :: Python :: 3
Classifier: Programming Language :: Python :: 3.11
Classifier: Programming Language :: Python :: 3.12
Classifier: Topic :: Scientific/Engineering
Requires-Python: >=3.11
License-File: LICENSE.txt
Requires-Dist: cachey
Requires-Dist: cartopy
Requires-Dist: cf_xarray
Requires-Dist: dask[complete]
Requires-Dist: datashader
Requires-Dist: matplotlib
Requires-Dist: mercantile
Requires-Dist: Pillow
Requires-Dist: scipy
Requires-Dist: xarray
Requires-Dist: xpublish>=0.4.0
Dynamic: license-file
